interact_test
interact
