Metadata-Version: 1.1
Name: galah-interact
Version: v0.2.1-
Summary: A Python framework for creating test harnesses to grade students' code.
Home-page: https://www.github.com/galah-group/galah-interact-python
Author: Galah Group LLC and other contributers
Author-email: jsull003@ucr.edu
License: Apache v2.0
Keywords: education framework
Platform: UNKNOWN
Classifier: Development Status :: 3 - Alpha
Classifier: Intended Audience :: Education
Classifier: Intended Audience :: Developers
Classifier: License :: OSI Approved :: Apache Software License
